[
  {
    "id": 1,
    "firstName": "Kevin",
    "lastName": "Sanz",
    "dateOfBirth": "2005-10-10T00:00:00",
    "classId": 1,
    "class": null
  },
  {
    "id": 2,
    "firstName": "Martin",
    "lastName": "Weber",
    "dateOfBirth": "2005-09-07T00:00:00",
    "classId": 1,
    "class": null
  },
  {
    "id": 3,
    "firstName": "Jorge",
    "lastName": "Il",
    "dateOfBirth": "2005-08-10T00:00:00",
    "classId": 1,
    "class": null
  },
  {
    "id": 4,
    "firstName": "Lisa",
    "lastName": "Miller",
    "dateOfBirth": "2005-05-04T00:00:00",
    "classId": 1,
    "class": null
  },
  {
    "id": 5,
    "firstName": "Run",
    "lastName": "Liu",
    "dateOfBirth": "2005-10-02T00:00:00",
    "classId": 1,
    "class": null
  },
  {
    "id": 6,
    "firstName": "Sean",
    "lastName": "Stewart",
    "dateOfBirth": "2003-02-08T00:00:00",
    "classId": 2,
    "class": null
  },
  {
    "id": 7,
    "firstName": "Olinda",
    "lastName": "Turner",
    "dateOfBirth": "2003-05-07T00:00:00",
    "classId": 2,
    "class": null
  },
  {
    "id": 8,
    "firstName": "Jon",
    "lastName": "Orton",
    "dateOfBirth": "2002-08-10T00:00:00",
    "classId": 2,
    "class": null
  },
  {
    "id": 9,
    "firstName": "Toby",
    "lastName": "Nixon",
    "dateOfBirth": "2002-12-05T00:00:00",
    "classId": 2,
    "class": null
  },
  {
    "id": 10,
    "firstName": "Daniela",
    "lastName": "Guinot",
    "dateOfBirth": "2002-08-01T00:00:00",
    "classId": 2,
    "class": null
  },
  {
    "id": 11,
    "firstName": "Vijay",
    "lastName": "Sundaram",
    "dateOfBirth": "2007-02-03T00:00:00",
    "classId": 3,
    "class": null
  },
  {
    "id": 12,
    "firstName": "Eric",
    "lastName": "Gruber",
    "dateOfBirth": "2007-05-06T00:00:00",
    "classId": 3,
    "class": null
  },
  {
    "id": 13,
    "firstName": "Chris",
    "lastName": "Meyer",
    "dateOfBirth": "2006-05-09T00:00:00",
    "classId": 3,
    "class": null
  },
  {
    "id": 14,
    "firstName": "Chen",
    "lastName": "Lu",
    "dateOfBirth": "2007-05-02T00:00:00",
    "classId": 3,
    "class": null
  },
  {
    "id": 15,
    "firstName": "Yan",
    "lastName": "Li",
    "dateOfBirth": "2007-03-03T00:00:00",
    "classId": 3,
    "class": null
  },
  {
    "id": 16,
    "firstName": "Borja",
    "lastName": "Cabeza",
    "dateOfBirth": "2008-12-12T00:00:00",
    "classId": 1,
    "class": null
  },
  {
    "id": 17,
    "firstName": "Ana",
    "lastName": "Sánchez Sanz",
    "dateOfBirth": "2006-05-09T00:00:00",
    "classId": 1,
    "class": null
  },
  {
    "id": 18,
    "firstName": "Ana",
    "lastName": "Sánchez",
    "dateOfBirth": "2006-05-09T00:00:00",
    "classId": 1,
    "class": null
  },
  {
    "id": 19,
    "firstName": "Juanma",
    "lastName": "Izquierdo",
    "dateOfBirth": "0001-01-01T00:00:00",
    "classId": 1,
    "class": null
  },
  {
    "id": 20,
    "firstName": "Francisco",
    "lastName": "Cabeza",
    "dateOfBirth": "2008-05-12T00:00:00",
    "classId": 2,
    "class": null
  },
  {
    "id": 21,
    "firstName": "David",
    "lastName": "SR",
    "dateOfBirth": "1992-07-26T00:00:00",
    "classId": 1,
    "class": null
  },
  {
    "id": 23,
    "firstName": "Juanma2 ",
    "lastName": "Izquierdo",
    "dateOfBirth": "0001-01-01T00:00:00",
    "classId": 1,
    "class": null
  },
  {
    "id": 24,
    "firstName": "Juanma3",
    "lastName": "Izquierdo",
    "dateOfBirth": "0001-01-01T00:00:00",
    "classId": 1,
    "class": null
  },
  {
    "id": 25,
    "firstName": "Aitor",
    "lastName": "Cerdan",
    "dateOfBirth": "2006-10-10T00:00:00",
    "classId": 1,
    "class": null
  },
  {
    "id": 26,
    "firstName": "Aitor",
    "lastName": "Cerdan",
    "dateOfBirth": "1994-10-14T00:00:00",
    "classId": 1,
    "class": null
  },
  {
    "id": 27,
    "firstName": "Ana",
    "lastName": "Sanchez",
    "dateOfBirth": "1992-05-02T00:00:00",
    "classId": 1,
    "class": null
  },
  {
    "id": 29,
    "firstName": "Alberto",
    "lastName": "González",
    "dateOfBirth": "1996-01-31T00:00:00",
    "classId": 1,
    "class": null
  },
  {
    "id": 30,
    "firstName": "Ly",
    "lastName": "Estevez",
    "dateOfBirth": "1993-06-03T00:00:00",
    "classId": 2,
    "class": null
  },
  {
    "id": 32,
    "firstName": "Prudencio",
    "lastName": "Fernandez",
    "dateOfBirth": "1967-09-23T00:00:00",
    "classId": 1,
    "class": null
  },
  {
    "id": 33,
    "firstName": "Jose",
    "lastName": "Izquierdo",
    "dateOfBirth": "1993-11-09T00:00:00",
    "classId": 1,
    "class": null
  },
  {
    "id": 36,
    "firstName": "Alberto",
    "lastName": "González",
    "dateOfBirth": "1996-01-31T00:00:00",
    "classId": 1,
    "class": null
  },
  {
    "id": 37,
    "firstName": "Danito",
    "lastName": "El Hay",
    "dateOfBirth": "1998-11-29T00:00:00",
    "classId": 2,
    "class": null
  },
  {
    "id": 38,
    "firstName": "Alberto",
    "lastName": "González",
    "dateOfBirth": "1996-01-31T00:00:00",
    "classId": 1,
    "class": null
  },
  {
    "id": 39,
    "firstName": "Aitor",
    "lastName": "Cerdan",
    "dateOfBirth": "1994-10-14T00:00:00",
    "classId": 1,
    "class": null
  },
  {
    "id": 45,
    "firstName": "Omar",
    "lastName": "García Prado",
    "dateOfBirth": "1994-05-31T00:00:00",
    "classId": 3,
    "class": null
  },
  {
    "id": 46,
    "firstName": "Darwin",
    "lastName": "Time",
    "dateOfBirth": "1986-04-29T00:00:00",
    "classId": 1,
    "class": null
  },
  {
    "id": 47,
    "firstName": "Valentina",
    "lastName": "Pinos",
    "dateOfBirth": "1966-03-15T00:00:00",
    "classId": 2,
    "class": null
  },
  {
    "id": 48,
    "firstName": "Pedro4",
    "lastName": "Hdez",
    "dateOfBirth": "1997-02-27T00:00:00",
    "classId": 1,
    "class": null
  },
  {
    "id": 49,
    "firstName": "Pedro4",
    "lastName": "Hernandez",
    "dateOfBirth": "1997-02-27T00:00:00",
    "classId": 1,
    "class": null
  },
  {
    "id": 50,
    "firstName": "Claudio",
    "lastName": "Domingo",
    "dateOfBirth": "2001-01-01T00:00:00",
    "classId": 3,
    "class": null
  },
  {
    "id": 51,
    "firstName": "Claudia",
    "lastName": "Molina",
    "dateOfBirth": "2001-01-01T00:00:00",
    "classId": 2,
    "class": null
  }
]